LICENSE
MANIFEST.in
README.rst
setup.cfg
setup.py
bauble/__init__.py
bauble/assistant.py
bauble/bauble.glade
bauble/bauble.ui
bauble/btypes.py
bauble/connmgr.glade
bauble/connmgr.py
bauble/db.py
bauble/editor.py
bauble/error.py
bauble/gettext_windows.py
bauble/i18n.py
bauble/meta.py
bauble/notes.glade
bauble/paths.py
bauble/pictures.glade
bauble/pictures_view.glade
bauble/pictures_view.py
bauble/pluginmgr.py
bauble/prefs.py
bauble/querybuilder.glade
bauble/querybuilder.py
bauble/querybuilderparser.py
bauble/search.py
bauble/task.py
bauble/test_querybuilderparser.py
bauble/ui.py
bauble/version.py
bauble/view.py
bauble/images/bauble.xpm
bauble/images/bauble_logo.png
bauble/images/calendar.png
bauble/images/ghini-tour.png
bauble/images/ghini-tour.svg
bauble/images/ghini.svg
bauble/images/ghini.xpm
bauble/images/ghini_logo.bmp
bauble/images/icon-square.svg
bauble/images/icon.ico
bauble/images/icon.png
bauble/images/icon.svg
bauble/images/icon128.png
bauble/images/icon2.png
bauble/images/icon24.png
bauble/images/loading.gif
bauble/images/menu-help-bug.png
bauble/images/prefs_general.png
bauble/images/prefs_security.png
bauble/plugins/__init__.py
bauble/plugins/abcd/__init__.py
bauble/plugins/abcd/abcd_2.06.xsd
bauble/plugins/abcd/new-abcd.png
bauble/plugins/abcd/test.py
bauble/plugins/garden/__init__.py
bauble/plugins/garden/acc_editor.glade
bauble/plugins/garden/acc_infobox.glade
bauble/plugins/garden/accession.py
bauble/plugins/garden/aggregateclient.py
bauble/plugins/garden/contact.glade
bauble/plugins/garden/exporttopocket.py
bauble/plugins/garden/import_pocket_log.py
bauble/plugins/garden/insert-new.png
bauble/plugins/garden/institution.glade
bauble/plugins/garden/institution.py
bauble/plugins/garden/loc_editor.glade
bauble/plugins/garden/loc_infobox.glade
bauble/plugins/garden/location.py
bauble/plugins/garden/picture_importer.glade
bauble/plugins/garden/picture_importer.py
bauble/plugins/garden/picture_importer_test.py
bauble/plugins/garden/plant.py
ghini.desktop.egg-info/PKG-INFO
ghini.desktop.egg-info/SOURCES.txt
ghini.desktop.egg-info/dependency_links.txt
ghini.desktop.egg-info/requires.txt
ghini.desktop.egg-info/top_level.txt
