Metadata-Version: 2.1
Name: ghini.desktop
Version: 3.1.7
Summary: Ghini: a biodiversity collection manager
Home-page: http://ghini.github.io/
Author: Mario Frasca
Author-email: mario@anche.no
License: GPLv2+
Keywords: database biodiversity botanic collection botany herbarium arboretum
Platform: UNKNOWN
Provides-Extra: docs
